imbox_sis/__init__.py
imbox_sis/imap.py
imbox_sis/imap.pyi
imbox_sis/imbox.py
imbox_sis/imbox.pyi
imbox_sis/messages.py
imbox_sis/messages.pyi
imbox_sis/parser.py
imbox_sis/parser.pyi
imbox_sis/query.py
imbox_sis/utils.py
imbox_sis/utils.pyi
imbox_sis/vendors/__init__.py
imbox_sis/vendors/__init__.pyi
imbox_sis/vendors/gmail.py
imbox_sis/vendors/gmail.pyi
imbox_sis/vendors/helpers.py
imbox_sis/version.py
imbox_sis-0.9.11.dist-info/WHEEL
imbox_sis-0.9.11.dist-info/METADATA
imbox_sis-0.9.11.dist-info/LICENSE
imbox_sis-0.9.11.dist-info/RECORD
